milligrad/NN.py
milligrad/__init__.py
milligrad/backend.py
milligrad/engine.py
milligrad-1.2.0.dist-info/METADATA
milligrad-1.2.0.dist-info/WHEEL
milligrad-1.2.0.dist-info/top_level.txt
milligrad-1.2.0.dist-info/RECORD
