Metadata-Version: 2.1
Name: milligrad
Version: 1.2.0
Summary: Basic neural network library
Home-page: https://github.com/LordMAF3/milligrad
Author: Manuel Ferrazzani
Author-email: manu.ferra.mf@gmail.com
License: MIT
Platform: UNKNOWN
Requires-Dist: graphviz
